pymicroconnectors/__init__.py
pymicroconnectors/config.py
pymicroconnectors/ebay.py
pymicroconnectors/flask.py
pymicroconnectors/flask_ask.py
pymicroconnectors/flask_assistant.py
pymicroconnectors/flask_graphql.py
pymicroconnectors/flask_restful.py
pymicroconnectors/handlebars.py
pymicroconnectors/helpers.py
pymicroconnectors/logger.py
pymicroconnectors/mongoengine.py
pymicroconnectors/prestashop.py
pymicroconnectors/spreedsheet.py
pymicroconnectors/sqlalchemy.py
pymicroconnectors-0.0.3.dist-info/METADATA
pymicroconnectors-0.0.3.dist-info/RECORD
pymicroconnectors-0.0.3.dist-info/WHEEL
pymicroconnectors-0.0.3.dist-info/top_level.txt
