Metadata-Version: 2.1
Name: pymicroconnectors
Version: 0.0.3
Summary: Make connection easier for your microservices
Home-page: https://github.com/ddelizia/pymicroconnectors
Author: Danilo Delizia
Author-email: ddelizia@gmail.com
License: UNKNOWN
Platform: UNKNOWN
Classifier: Programming Language :: Python :: 3
Classifier: License :: OSI Approved :: MIT License
Classifier: Operating System :: OS Independent
Requires-Dist: pybars3
Requires-Dist: requests
Requires-Dist: figgypy
Requires-Dist: colorlog
Requires-Dist: google-api-python-client
Requires-Dist: oauth2client
Requires-Dist: pipenv
Requires-Dist: ebaysdk
Requires-Dist: mongoengine
Requires-Dist: flask
Requires-Dist: flask-restful
Requires-Dist: flask-graphql
Requires-Dist: flask-restful-swagger
Requires-Dist: flask-restful-swagger-2
Requires-Dist: sqlalchemy
Requires-Dist: gunicorn
Requires-Dist: flask-ask (==0.8.9)
Requires-Dist: click
Requires-Dist: flask-assistant
